MANIFEST.in
README.rst
boatdctl
setup.py
boatdclient/__init__.py
boatdclient/bearing.py
boatdclient/boatd_client.py
boatdclient/point.py
python_boatdclient.egg-info/PKG-INFO
python_boatdclient.egg-info/SOURCES.txt
python_boatdclient.egg-info/dependency_links.txt
python_boatdclient.egg-info/top_level.txt