Metadata-Version: 1.1
Name: python-boatdclient
Version: 0.9.0
Summary: Python wrapper for the boatd API, used to write behavior scripts.
Home-page: https://github.com/boatd/python-boatd
Author: Louis Taylor
Author-email: louis@kragniz.eu
License: GPL
Keywords: boat sailing wrapper rest
Platform: UNKNOWN
Classifier: Development Status :: 3 - Alpha
Classifier: Intended Audience :: Developers
Classifier: Topic :: Software Development :: Libraries :: Python Modules
Classifier: License :: OSI Approved :: GNU General Public License v3 (GPLv3)
